rpi_arduino_pin/ module.py
rpi_arduino_pin/__init__.py
rpi_arduino_pin/core.py
rpi_arduino_pin-0.2.4.dist-info/licenses/LICENSE
rpi_arduino_pin-0.2.4.dist-info/METADATA
rpi_arduino_pin-0.2.4.dist-info/WHEEL
rpi_arduino_pin-0.2.4.dist-info/top_level.txt
rpi_arduino_pin-0.2.4.dist-info/RECORD
