Metadata-Version: 2.4
Name: rpi-arduino-pin
Version: 0.2.4
Summary: A Python library for controlling Raspberry Pi GPIO, I2C, SPI and communicating with Arduino via serial.
Home-page: https://github.com/SKARCH218/pin
Author: Taehun Kim
Author-email: kimheuu0218@gmail.com
Classifier: Programming Language :: Python :: 3
Classifier: License :: OSI Approved :: MIT License
Classifier: Operating System :: POSIX :: Linux
Classifier: Development Status :: 3 - Alpha
Classifier: Intended Audience :: Developers
Classifier: Topic :: Software Development :: Embedded Systems
Classifier: Topic :: Home Automation
Requires-Python: >=3.6
License-File: LICENSE
Requires-Dist: lgpio
Requires-Dist: pyserial
Requires-Dist: gpiozero
Requires-Dist: spidev
Dynamic: author
Dynamic: author-email
Dynamic: classifier
Dynamic: description
Dynamic: description-content-type
Dynamic: home-page
Dynamic: license-file
Dynamic: requires-dist
Dynamic: requires-python
Dynamic: summary
